schoolsoft_api/__init__.py
schoolsoft_api/__version__.py
schoolsoft_api/schoolsoft_api.py
schoolsoft_api-1.0.3.dist-info/METADATA
schoolsoft_api-1.0.3.dist-info/WHEEL
schoolsoft_api-1.0.3.dist-info/top_level.txt
schoolsoft_api-1.0.3.dist-info/RECORD
