Metadata-Version: 2.1
Name: schoolsoft-api
Version: 1.0.3
Summary: Communicate with the official schoolsoft api
Home-page: https://github.com/Blatzar/schoolsoft-api-app
Author: Blatzar
Author-email: blatzar@gmail.com
License: UNKNOWN
Keywords: schoolsoft,schedule,lunch,api
Platform: UNKNOWN
Requires-Dist: requests
Requires-Dist: datetime
